{
    "0xC153E5BCCF411814": {
        "name": "HAS_BULLET_IMPACTED_IN_AREA",
        "comment": "p3 - possibly radius?",
        "params": [
            {
                "type": "float",
                "name": "x"
            },
            {
                "type": "float",
                "name": "y"
            },
            {
                "type": "float",
                "name": "z"
            },
            {
                "type": "float",
                "name": "p3"
            },
            {
                "type": "BOOL",
                "name": "p4"
            },
            {
                "type": "BOOL",
                "name": "p5"
            }
        ],
        "return_type": "BOOL",
        "build": "1207",
        "examples": []
    }
}